cz_commitizen_youtrack/__init__.py
cz_commitizen_youtrack/__version__.py
cz_commitizen_youtrack/cz_commitizen_youtrack.py
cz_commitizen_youtrack-0.0.16.dist-info/LICENSE
cz_commitizen_youtrack-0.0.16.dist-info/METADATA
cz_commitizen_youtrack-0.0.16.dist-info/WHEEL
cz_commitizen_youtrack-0.0.16.dist-info/entry_points.txt
cz_commitizen_youtrack-0.0.16.dist-info/top_level.txt
cz_commitizen_youtrack-0.0.16.dist-info/RECORD
