Metadata-Version: 2.1
Name: cz_commitizen_youtrack
Version: 0.0.16
Home-page: https://github.com/CanisHelix/cz-youtrack
Author: Nigel George
Author-email: nigel.george@shiroikuma.co.uk
License: MIT
Classifier: Programming Language :: Python :: 3
Classifier: License :: OSI Approved :: MIT License
Classifier: Operating System :: OS Independent
License-File: LICENSE
Requires-Dist: commitizen
